medit/__init__.py
medit/cli.py
medit/medit.ui
medit/meditor.py
medit/mview.py
medit/styles/__init__.py
medit/styles/external/github-markdown-dark.css
medit/styles/external/github-markdown-light.css
medit/styles/external/github-markdown.css
medit/styles/external/pygments-solarized-style/solarized-dark.css
medit/styles/external/pygments-solarized-style/solarized-light.css
medit/styles/external/retro.css
medit/styles/external/solarized-dark-all-sites.css
medit/styles/external/solarized-light-all-sites.css
medit/styles/external/thomasf-solarized-css/solarized-dark.css
medit/styles/external/thomasf-solarized-css/solarized-light.css
medit/styles/markdown.min.css
medit/styles/pygments/abap.css
medit/styles/pygments/algol.css
medit/styles/pygments/algol_nu.css
medit/styles/pygments/arduino.css
medit/styles/pygments/autumn.css
medit/styles/pygments/borland.css
medit/styles/pygments/bw.css
medit/styles/pygments/colorful.css
medit/styles/pygments/default.css
medit/styles/pygments/dracula.css
medit/styles/pygments/emacs.css
medit/styles/pygments/friendly.css
medit/styles/pygments/friendly_grayscale.css
medit/styles/pygments/fruity.css
medit/styles/pygments/igor.css
medit/styles/pygments/inkpot.css
medit/styles/pygments/lilypond.css
medit/styles/pygments/lovelace.css
medit/styles/pygments/manni.css
medit/styles/pygments/material.css
medit/styles/pygments/monokai.css
medit/styles/pygments/murphy.css
medit/styles/pygments/native.css
medit/styles/pygments/nord.css
medit/styles/pygments/pastie.css
medit/styles/pygments/perldoc.css
medit/styles/pygments/rainbow_dash.css
medit/styles/pygments/rrt.css
medit/styles/pygments/sas.css
medit/styles/pygments/staroffice.css
medit/styles/pygments/tango.css
medit/styles/pygments/trac.css
medit/styles/pygments/vim.css
medit/styles/pygments/vs.css
medit/styles/pygments/xcode.css
medit/styles/pygments/zenburn.css
medit/ui.py
medit/utils.py
medit-0.0.11.dist-info/METADATA
medit-0.0.11.dist-info/WHEEL
medit-0.0.11.dist-info/entry_points.txt
medit-0.0.11.dist-info/RECORD
