Metadata-Version: 2.1
Name: medit
Version: 0.0.11
Summary: Markup Editor
Home-page: https://projects.om-office.de/frans/medit.git
Author: Frans Fürst
Author-email: frans.fuerst+gitlab@protonmail.com
Requires-Python: >=3.9,<3.12
Classifier: Programming Language :: Python :: 3
Classifier: Programming Language :: Python :: 3.9
Classifier: Programming Language :: Python :: 3.10
Classifier: Programming Language :: Python :: 3.11
Requires-Dist: asyncinotify (>=4.0.1,<5.0.0)
Requires-Dist: markdown (<3.2)
Requires-Dist: markdown-checklist (>=0.4.4,<0.5.0)
Requires-Dist: markdown-include (>=0.8.1,<0.9.0)
Requires-Dist: md-mermaid (>=0.1.1,<0.2.0)
Requires-Dist: pygments (>=2.15.1,<3.0.0)
Requires-Dist: pyqt6 (>=6.5.1,<7.0.0)
Requires-Dist: pyqt6-qscintilla (>=2.14.0,<3.0.0)
Requires-Dist: pyqt6-webengine (>=6.5.0,<7.0.0)
Requires-Dist: pyqtdarktheme (>=2.1.0,<3.0.0)
Requires-Dist: toml (>=0.10.2,<0.11.0)
Project-URL: Repository, https://projects.om-office.de/frans/medit.git
